{
	"@type":"Process",
	"Name":"import_assumptions",
	"HasSecurityAccess":true,
	"Code@Code.link":"import_assumptions.ti",
	"UIData":"_ParseParams={&quotmeasures&quot:[]&#044&quothasHeader&quot:&quottrue&quot&#044&quotnumColumns&quot:&quot21&quot&#044&quotskipRows&quot:&quot0&quot&#044&quotlocale&quot:{&quotlanguange&quot:&quoten&quot&#044&quotvariant&quot:&quot&quot&#044&quotcountry&quot:&quotUS&quot}&#044&quotdimensions&quot:[{&quotdimensionType&quot:&quotGENERIC&quot&#044&quotleafSortDirection&quot:&quotDECENDING&quot&#044&quotconsolidatedSortDirection&quot:&quotDECENDING&quot&#044&quotqualifyHierarchy&quot:true&#044&quotcreateTotalRoot&quot:false&#044&quotinvariantName&quot:&quotAssumptions&quot&#044&quotlevels&quot:[{&quotcolumnType&quot:&quotSTRING&quot&#044&quotsourceColumn&quot:0&#044&quotcolumnName&quot:&quotAssumptions&quot&#044&quotelementWeight&quot:&quot1&quot&#044&quotlabel&quot:&quotAssumptions&quot&#044&quotattributes&quot:[{&quotcolumnType&quot:&quotSTRING&quot&#044&quotsourceColumn&quot:1&#044&quotcolumnName&quot:&quotP\\u0159edpoklady_CS&quot&#044&quotlabel&quot:&quotP\\u0159edpoklady_CS&quot&#044&quotisAlias&quot:&quottrue&quot&#044&quotexpression&quot:null&#044&quotinvariantName&quot:&quot&quot&#044&quotexists&quot:true}&#044{&quotcolumnType&quot:&quotSTRING&quot&#044&quotsourceColumn&quot:2&#044&quotcolumnName&quot:&quotForuds\\u00e6tninger_DA&quot&#044&quotlabel&quot:&quotForuds\\u00e6tninger_DA&quot&#044&quotisAlias&quot:&quottrue&quot&#044&quotexpression&quot:null&#044&quotinvariantName&quot:&quot&quot&#044&quotexists&quot:true}&#044{&quotcolumnType&quot:&quotSTRING&quot&#044&quotsourceColumn&quot:3&#044&quotcolumnName&quot:&quot\\u00dcbernahmen_DE&quot&#044&quotlabel&quot:&quot\\u00dcbernahmen_DE&quot&#044&quotisAlias&quot:&quottrue&quot&#044&quotexpression&quot:null&#044&quotinvariantName&quot:&quot&quot&#044&quotexists&quot:true}&#044{&quotcolumnType&quot:&quotSTRING&quot&#044&quotsourceColumn&quot:4&#044&quotcolumnName&quot:&quotSuposiciones_ES&quot&#044&quotlabel&quot:&quotSuposiciones_ES&quot&#044&quotisAlias&quot:&quottrue&quot&#044&quotexpression&quot:null&#044&quotinvariantName&quot:&quot&quot&#044&quotexists&quot:true}&#044{&quotcolumnType&quot:&quotSTRING&quot&#044&quotsourceColumn&quot:5&#044&quotcolumnName&quot:&quotOletukset_FI&quot&#044&quotlabel&quot:&quotOletukset_FI&quot&#044&quotisAlias&quot:&quottrue&quot&#044&quotexpression&quot:null&#044&quotinvariantName&quot:&quot&quot&#044&quotexists&quot:true}&#044{&quotcolumnType&quot:&quotSTRING&quot&#044&quotsourceColumn&quot:6&#044&quotcolumnName&quot:&quotHypoth\\u00e8ses_FR&quot&#044&quotlabel&quot:&quotHypoth\\u00e8ses_FR&quot&#044&quotisAlias&quot:&quottrue&quot&#044&quotexpression&quot:null&#044&quotinvariantName&quot:&quot&quot&#044&quotexists&quot:true}&#044{&quotcolumnType&quot:&quotSTRING&quot&#044&quotsourceColumn&quot:7&#044&quotcolumnName&quot:&quot\\u63a8\\u5b9a_JA&quot&#044&quotlabel&quot:&quot\\u63a8\\u5b9a_JA&quot&#044&quotisAlias&quot:&quottrue&quot&#044&quotexpression&quot:null&#044&quotinvariantName&quot:&quot&quot&#044&quotexists&quot:true}&#044{&quotcolumnType&quot:&quotSTRING&quot&#044&quotsourceColumn&quot:8&#044&quotcolumnName&quot:&quotPretpostavke_HR&quot&#044&quotlabel&quot:&quotPretpostavke_HR&quot&#044&quotisAlias&quot:&quottrue&quot&#044&quotexpression&quot:null&#044&quotinvariantName&quot:&quot&quot&#044&quotexists&quot:true}&#044{&quotcolumnType&quot:&quotSTRING&quot&#044&quotsourceColumn&quot:9&#044&quotcolumnName&quot:&quotFelt\\u00e9telez\\u00e9sek_HU&quot&#044&quotlabel&quot:&quotFelt\\u00e9telez\\u00e9sek_HU&quot&#044&quotisAlias&quot:&quottrue&quot&#044&quotexpression&quot:null&#044&quotinvariantName&quot:&quot&quot&#044&quotexists&quot:true}&#044{&quotcolumnType&quot:&quotSTRING&quot&#044&quotsourceColumn&quot:10&#044&quotcolumnName&quot:&quotPresupposti_IT&quot&#044&quotlabel&quot:&quotPresupposti_IT&quot&#044&quotisAlias&quot:&quottrue&quot&#044&quotexpression&quot:null&#044&quotinvariantName&quot:&quot&quot&#044&quotexists&quot:true}&#044{&quotcolumnType&quot:&quotSTRING&quot&#044&quotsourceColumn&quot:11&#044&quotcolumnName&quot:&quot\\ucd94\\uc815_KO&quot&#044&quotlabel&quot:&quot\\ucd94\\uc815_KO&quot&#044&quotisAlias&quot:&quottrue&quot&#044&quotexpression&quot:null&#044&quotinvariantName&quot:&quot&quot&#044&quotexists&quot:true}&#044{&quotcolumnType&quot:&quotSTRING&quot&#044&quotsourceColumn&quot:12&#044&quotcolumnName&quot:&quotForutsetninger_NO&quot&#044&quotlabel&quot:&quotForutsetninger_NO&quot&#044&quotisAlias&quot:&quottrue&quot&#044&quotexpression&quot:null&#044&quotinvariantName&quot:&quot&quot&#044&quotexists&quot:true}&#044{&quotcolumnType&quot:&quotSTRING&quot&#044&quotsourceColumn&quot:13&#044&quotcolumnName&quot:&quotZa\\u0142o\\u017cenia_PL&quot&#044&quotlabel&quot:&quotZa\\u0142o\\u017cenia_PL&quot&#044&quotisAlias&quot:&quottrue&quot&#044&quotexpression&quot:null&#044&quotinvariantName&quot:&quot&quot&#044&quotexists&quot:true}&#044{&quotcolumnType&quot:&quotSTRING&quot&#044&quotsourceColumn&quot:14&#044&quotcolumnName&quot:&quotSuposi\\u00e7\\u00f5es_PT&quot&#044&quotlabel&quot:&quotSuposi\\u00e7\\u00f5es_PT&quot&#044&quotisAlias&quot:&quottrue&quot&#044&quotexpression&quot:null&#044&quotinvariantName&quot:&quot&quot&#044&quotexists&quot:true}&#044{&quotcolumnType&quot:&quotSTRING&quot&#044&quotsourceColumn&quot:15&#044&quotcolumnName&quot:&quotSupozi\\u0163ii_RO&quot&#044&quotlabel&quot:&quotSupozi\\u0163ii_RO&quot&#044&quotisAlias&quot:&quottrue&quot&#044&quotexpression&quot:null&#044&quotinvariantName&quot:&quot&quot&#044&quotexists&quot:true}&#044{&quotcolumnType&quot:&quotSTRING&quot&#044&quotsourceColumn&quot:16&#044&quotcolumnName&quot:&quot\\u041f\\u0440\\u0435\\u0434\\u043f\\u043e\\u043b\\u043e\\u0436\\u0435\\u043d\\u0438\\u044f_RU&quot&#044&quotlabel&quot:&quot\\u041f\\u0440\\u0435\\u0434\\u043f\\u043e\\u043b\\u043e\\u0436\\u0435\\u043d\\u0438\\u044f_RU&quot&#044&quotisAlias&quot:&quottrue&quot&#044&quotexpression&quot:null&#044&quotinvariantName&quot:&quot&quot&#044&quotexists&quot:true}&#044{&quotcolumnType&quot:&quotSTRING&quot&#044&quotsourceColumn&quot:17&#044&quotcolumnName&quot:&quot\\u5047\\u8bbe_SC&quot&#044&quotlabel&quot:&quot\\u5047\\u8bbe_SC&quot&#044&quotisAlias&quot:&quottrue&quot&#044&quotexpression&quot:null&#044&quotinvariantName&quot:&quot&quot&#044&quotexists&quot:true}&#044{&quotcolumnType&quot:&quotSTRING&quot&#044&quotsourceColumn&quot:18&#044&quotcolumnName&quot:&quotAntaganden_SV&quot&#044&quotlabel&quot:&quotAntaganden_SV&quot&#044&quotisAlias&quot:&quottrue&quot&#044&quotexpression&quot:null&#044&quotinvariantName&quot:&quot&quot&#044&quotexists&quot:true}&#044{&quotcolumnType&quot:&quotSTRING&quot&#044&quotsourceColumn&quot:19&#044&quotcolumnName&quot:&quot\\u5047\\u8a2d_TC&quot&#044&quotlabel&quot:&quot\\u5047\\u8a2d_TC&quot&#044&quotisAlias&quot:&quottrue&quot&#044&quotexpression&quot:null&#044&quotinvariantName&quot:&quot&quot&#044&quotexists&quot:true}&#044{&quotcolumnType&quot:&quotSTRING&quot&#044&quotsourceColumn&quot:20&#044&quotcolumnName&quot:&quotVarsay\\u0131mlar_TR&quot&#044&quotlabel&quot:&quotVarsay\\u0131mlar_TR&quot&#044&quotisAlias&quot:&quottrue&quot&#044&quotexpression&quot:null&#044&quotinvariantName&quot:&quot&quot&#044&quotexists&quot:true}]&#044&quotexpression&quot:null&#044&quotexists&quot:true}]&#044&quotisMeasureDimension&quot:false&#044&quotparentChild&quot:false&#044&quotconsolidatedSortType&quot:&quotNONE&quot&#044&quotstrategy&quot:&quotMERGE&quot&#044&quotlabel&quot:&quotAssumptions&quot&#044&quotisMemberUpdateStrategyChanged&quot:false&#044&quotleafSortType&quot:&quotNONE&quot&#044&quotattributes&quot:[{&quotcolumnType&quot:&quotSTRING&quot&#044&quotsourceColumn&quot:1&#044&quotcolumnName&quot:&quotP\\u0159edpoklady_CS&quot&#044&quotlabel&quot:&quotP\\u0159edpoklady_CS&quot&#044&quotisAlias&quot:&quottrue&quot&#044&quotexpression&quot:null&#044&quotinvariantName&quot:&quot&quot&#044&quotexists&quot:true}&#044{&quotcolumnType&quot:&quotSTRING&quot&#044&quotsourceColumn&quot:2&#044&quotcolumnName&quot:&quotForuds\\u00e6tninger_DA&quot&#044&quotlabel&quot:&quotForuds\\u00e6tninger_DA&quot&#044&quotisAlias&quot:&quottrue&quot&#044&quotexpression&quot:null&#044&quotinvariantName&quot:&quot&quot&#044&quotexists&quot:true}&#044{&quotcolumnType&quot:&quotSTRING&quot&#044&quotsourceColumn&quot:3&#044&quotcolumnName&quot:&quot\\u00dcbernahmen_DE&quot&#044&quotlabel&quot:&quot\\u00dcbernahmen_DE&quot&#044&quotisAlias&quot:&quottrue&quot&#044&quotexpression&quot:null&#044&quotinvariantName&quot:&quot&quot&#044&quotexists&quot:true}&#044{&quotcolumnType&quot:&quotSTRING&quot&#044&quotsourceColumn&quot:4&#044&quotcolumnName&quot:&quotSuposiciones_ES&quot&#044&quotlabel&quot:&quotSuposiciones_ES&quot&#044&quotisAlias&quot:&quottrue&quot&#044&quotexpression&quot:null&#044&quotinvariantName&quot:&quot&quot&#044&quotexists&quot:true}&#044{&quotcolumnType&quot:&quotSTRING&quot&#044&quotsourceColumn&quot:5&#044&quotcolumnName&quot:&quotOletukset_FI&quot&#044&quotlabel&quot:&quotOletukset_FI&quot&#044&quotisAlias&quot:&quottrue&quot&#044&quotexpression&quot:null&#044&quotinvariantName&quot:&quot&quot&#044&quotexists&quot:true}&#044{&quotcolumnType&quot:&quotSTRING&quot&#044&quotsourceColumn&quot:6&#044&quotcolumnName&quot:&quotHypoth\\u00e8ses_FR&quot&#044&quotlabel&quot:&quotHypoth\\u00e8ses_FR&quot&#044&quotisAlias&quot:&quottrue&quot&#044&quotexpression&quot:null&#044&quotinvariantName&quot:&quot&quot&#044&quotexists&quot:true}&#044{&quotcolumnType&quot:&quotSTRING&quot&#044&quotsourceColumn&quot:7&#044&quotcolumnName&quot:&quot\\u63a8\\u5b9a_JA&quot&#044&quotlabel&quot:&quot\\u63a8\\u5b9a_JA&quot&#044&quotisAlias&quot:&quottrue&quot&#044&quotexpression&quot:null&#044&quotinvariantName&quot:&quot&quot&#044&quotexists&quot:true}&#044{&quotcolumnType&quot:&quotSTRING&quot&#044&quotsourceColumn&quot:8&#044&quotcolumnName&quot:&quotPretpostavke_HR&quot&#044&quotlabel&quot:&quotPretpostavke_HR&quot&#044&quotisAlias&quot:&quottrue&quot&#044&quotexpression&quot:null&#044&quotinvariantName&quot:&quot&quot&#044&quotexists&quot:true}&#044{&quotcolumnType&quot:&quotSTRING&quot&#044&quotsourceColumn&quot:9&#044&quotcolumnName&quot:&quotFelt\\u00e9telez\\u00e9sek_HU&quot&#044&quotlabel&quot:&quotFelt\\u00e9telez\\u00e9sek_HU&quot&#044&quotisAlias&quot:&quottrue&quot&#044&quotexpression&quot:null&#044&quotinvariantName&quot:&quot&quot&#044&quotexists&quot:true}&#044{&quotcolumnType&quot:&quotSTRING&quot&#044&quotsourceColumn&quot:10&#044&quotcolumnName&quot:&quotPresupposti_IT&quot&#044&quotlabel&quot:&quotPresupposti_IT&quot&#044&quotisAlias&quot:&quottrue&quot&#044&quotexpression&quot:null&#044&quotinvariantName&quot:&quot&quot&#044&quotexists&quot:true}&#044{&quotcolumnType&quot:&quotSTRING&quot&#044&quotsourceColumn&quot:11&#044&quotcolumnName&quot:&quot\\ucd94\\uc815_KO&quot&#044&quotlabel&quot:&quot\\ucd94\\uc815_KO&quot&#044&quotisAlias&quot:&quottrue&quot&#044&quotexpression&quot:null&#044&quotinvariantName&quot:&quot&quot&#044&quotexists&quot:true}&#044{&quotcolumnType&quot:&quotSTRING&quot&#044&quotsourceColumn&quot:12&#044&quotcolumnName&quot:&quotForutsetninger_NO&quot&#044&quotlabel&quot:&quotForutsetninger_NO&quot&#044&quotisAlias&quot:&quottrue&quot&#044&quotexpression&quot:null&#044&quotinvariantName&quot:&quot&quot&#044&quotexists&quot:true}&#044{&quotcolumnType&quot:&quotSTRING&quot&#044&quotsourceColumn&quot:13&#044&quotcolumnName&quot:&quotZa\\u0142o\\u017cenia_PL&quot&#044&quotlabel&quot:&quotZa\\u0142o\\u017cenia_PL&quot&#044&quotisAlias&quot:&quottrue&quot&#044&quotexpression&quot:null&#044&quotinvariantName&quot:&quot&quot&#044&quotexists&quot:true}&#044{&quotcolumnType&quot:&quotSTRING&quot&#044&quotsourceColumn&quot:14&#044&quotcolumnName&quot:&quotSuposi\\u00e7\\u00f5es_PT&quot&#044&quotlabel&quot:&quotSuposi\\u00e7\\u00f5es_PT&quot&#044&quotisAlias&quot:&quottrue&quot&#044&quotexpression&quot:null&#044&quotinvariantName&quot:&quot&quot&#044&quotexists&quot:true}&#044{&quotcolumnType&quot:&quotSTRING&quot&#044&quotsourceColumn&quot:15&#044&quotcolumnName&quot:&quotSupozi\\u0163ii_RO&quot&#044&quotlabel&quot:&quotSupozi\\u0163ii_RO&quot&#044&quotisAlias&quot:&quottrue&quot&#044&quotexpression&quot:null&#044&quotinvariantName&quot:&quot&quot&#044&quotexists&quot:true}&#044{&quotcolumnType&quot:&quotSTRING&quot&#044&quotsourceColumn&quot:16&#044&quotcolumnName&quot:&quot\\u041f\\u0440\\u0435\\u0434\\u043f\\u043e\\u043b\\u043e\\u0436\\u0435\\u043d\\u0438\\u044f_RU&quot&#044&quotlabel&quot:&quot\\u041f\\u0440\\u0435\\u0434\\u043f\\u043e\\u043b\\u043e\\u0436\\u0435\\u043d\\u0438\\u044f_RU&quot&#044&quotisAlias&quot:&quottrue&quot&#044&quotexpression&quot:null&#044&quotinvariantName&quot:&quot&quot&#044&quotexists&quot:true}&#044{&quotcolumnType&quot:&quotSTRING&quot&#044&quotsourceColumn&quot:17&#044&quotcolumnName&quot:&quot\\u5047\\u8bbe_SC&quot&#044&quotlabel&quot:&quot\\u5047\\u8bbe_SC&quot&#044&quotisAlias&quot:&quottrue&quot&#044&quotexpression&quot:null&#044&quotinvariantName&quot:&quot&quot&#044&quotexists&quot:true}&#044{&quotcolumnType&quot:&quotSTRING&quot&#044&quotsourceColumn&quot:18&#044&quotcolumnName&quot:&quotAntaganden_SV&quot&#044&quotlabel&quot:&quotAntaganden_SV&quot&#044&quotisAlias&quot:&quottrue&quot&#044&quotexpression&quot:null&#044&quotinvariantName&quot:&quot&quot&#044&quotexists&quot:true}&#044{&quotcolumnType&quot:&quotSTRING&quot&#044&quotsourceColumn&quot:19&#044&quotcolumnName&quot:&quot\\u5047\\u8a2d_TC&quot&#044&quotlabel&quot:&quot\\u5047\\u8a2d_TC&quot&#044&quotisAlias&quot:&quottrue&quot&#044&quotexpression&quot:null&#044&quotinvariantName&quot:&quot&quot&#044&quotexists&quot:true}&#044{&quotcolumnType&quot:&quotSTRING&quot&#044&quotsourceColumn&quot:20&#044&quotcolumnName&quot:&quotVarsay\\u0131mlar_TR&quot&#044&quotlabel&quot:&quotVarsay\\u0131mlar_TR&quot&#044&quotisAlias&quot:&quottrue&quot&#044&quotexpression&quot:null&#044&quotinvariantName&quot:&quot&quot&#044&quotexists&quot:true}]&#044&quotqualifySeparator&quot:&quot&#044 &quot&#044&quotexists&quot:true}]}€_DeployParams={&quotdataAction&quot:&quotACCUMULATE&quot&#044&quotclass&quot:&quotDeployParams&quot&#044&quotdimensionConflictResolutions&quot:{}}€",
	"VariablesUIData":
	[
		"_DimCaption=Assumptions€_DimType=GENERIC€VarType=32€ColType=825€VarDimension=Assumptions€VarDimOrder=1€VarDimAction=Update€VarElemType=Numeric€VarDimElemSortType=ByInput€VarDimElemSortSense=DESCENDING€_LevelCaption=Assumptions€_UserVisible=v_Assumptions_0€_UILabel=Assumptions€_DataType=STRING€_SourceIndex=0€",
		"VarType=32€ColType=841€AttributeDim=Assumptions€AttributeElemVar=v_Assumptions_0€AttributeAction=Update€AttributeName=P?edpoklady_CS€AttributeType=Alias€_UserVisible=v_P_edpoklady_CS_1€_UILabel=P?edpoklady_CS€_DataType=STRING€_SourceIndex=1€",
		"VarType=32€ColType=841€AttributeDim=Assumptions€AttributeElemVar=v_Assumptions_0€AttributeAction=Update€AttributeName=Forudsætninger_DA€AttributeType=Alias€_UserVisible=v_Foruds_tninger_DA_2€_UILabel=Forudsætninger_DA€_DataType=STRING€_SourceIndex=2€",
		"VarType=32€ColType=841€AttributeDim=Assumptions€AttributeElemVar=v_Assumptions_0€AttributeAction=Update€AttributeName=Übernahmen_DE€AttributeType=Alias€_UserVisible=v__bernahmen_DE_3€_UILabel=Übernahmen_DE€_DataType=STRING€_SourceIndex=3€",
		"VarType=32€ColType=841€AttributeDim=Assumptions€AttributeElemVar=v_Assumptions_0€AttributeAction=Update€AttributeName=Suposiciones_ES€AttributeType=Alias€_UserVisible=v_Suposiciones_ES_4€_UILabel=Suposiciones_ES€_DataType=STRING€_SourceIndex=4€",
		"VarType=32€ColType=841€AttributeDim=Assumptions€AttributeElemVar=v_Assumptions_0€AttributeAction=Update€AttributeName=Oletukset_FI€AttributeType=Alias€_UserVisible=v_Oletukset_FI_5€_UILabel=Oletukset_FI€_DataType=STRING€_SourceIndex=5€",
		"VarType=32€ColType=841€AttributeDim=Assumptions€AttributeElemVar=v_Assumptions_0€AttributeAction=Update€AttributeName=Hypothèses_FR€AttributeType=Alias€_UserVisible=v_Hypoth_ses_FR_6€_UILabel=Hypothèses_FR€_DataType=STRING€_SourceIndex=6€",
		"VarType=32€ColType=841€AttributeDim=Assumptions€AttributeElemVar=v_Assumptions_0€AttributeAction=Update€AttributeName=??_JA€AttributeType=Alias€_UserVisible=v____JA_7€_UILabel=??_JA€_DataType=STRING€_SourceIndex=7€",
		"VarType=32€ColType=841€AttributeDim=Assumptions€AttributeElemVar=v_Assumptions_0€AttributeAction=Update€AttributeName=Pretpostavke_HR€AttributeType=Alias€_UserVisible=v_Pretpostavke_HR_8€_UILabel=Pretpostavke_HR€_DataType=STRING€_SourceIndex=8€",
		"VarType=32€ColType=841€AttributeDim=Assumptions€AttributeElemVar=v_Assumptions_0€AttributeAction=Update€AttributeName=Feltételezések_HU€AttributeType=Alias€_UserVisible=v_Felt_telez_sek_HU_9€_UILabel=Feltételezések_HU€_DataType=STRING€_SourceIndex=9€",
		"VarType=32€ColType=841€AttributeDim=Assumptions€AttributeElemVar=v_Assumptions_0€AttributeAction=Update€AttributeName=Presupposti_IT€AttributeType=Alias€_UserVisible=v_Presupposti_IT_10€_UILabel=Presupposti_IT€_DataType=STRING€_SourceIndex=10€",
		"VarType=32€ColType=841€AttributeDim=Assumptions€AttributeElemVar=v_Assumptions_0€AttributeAction=Update€AttributeName=??_KO€AttributeType=Alias€_UserVisible=v____KO_11€_UILabel=??_KO€_DataType=STRING€_SourceIndex=11€",
		"VarType=32€ColType=841€AttributeDim=Assumptions€AttributeElemVar=v_Assumptions_0€AttributeAction=Update€AttributeName=Forutsetninger_NO€AttributeType=Alias€_UserVisible=v_Forutsetninger_NO_12€_UILabel=Forutsetninger_NO€_DataType=STRING€_SourceIndex=12€",
		"VarType=32€ColType=841€AttributeDim=Assumptions€AttributeElemVar=v_Assumptions_0€AttributeAction=Update€AttributeName=Za?o?enia_PL€AttributeType=Alias€_UserVisible=v_Za_o_enia_PL_13€_UILabel=Za?o?enia_PL€_DataType=STRING€_SourceIndex=13€",
		"VarType=32€ColType=841€AttributeDim=Assumptions€AttributeElemVar=v_Assumptions_0€AttributeAction=Update€AttributeName=Suposições_PT€AttributeType=Alias€_UserVisible=v_Suposi__es_PT_14€_UILabel=Suposições_PT€_DataType=STRING€_SourceIndex=14€",
		"VarType=32€ColType=841€AttributeDim=Assumptions€AttributeElemVar=v_Assumptions_0€AttributeAction=Update€AttributeName=Supozi?ii_RO€AttributeType=Alias€_UserVisible=v_Supozi_ii_RO_15€_UILabel=Supozi?ii_RO€_DataType=STRING€_SourceIndex=15€",
		"VarType=32€ColType=841€AttributeDim=Assumptions€AttributeElemVar=v_Assumptions_0€AttributeAction=Update€AttributeName=?????????????_RU€AttributeType=Alias€_UserVisible=v_______________RU_16€_UILabel=?????????????_RU€_DataType=STRING€_SourceIndex=16€",
		"VarType=32€ColType=841€AttributeDim=Assumptions€AttributeElemVar=v_Assumptions_0€AttributeAction=Update€AttributeName=??_SC€AttributeType=Alias€_UserVisible=v____SC_17€_UILabel=??_SC€_DataType=STRING€_SourceIndex=17€",
		"VarType=32€ColType=841€AttributeDim=Assumptions€AttributeElemVar=v_Assumptions_0€AttributeAction=Update€AttributeName=Antaganden_SV€AttributeType=Alias€_UserVisible=v_Antaganden_SV_18€_UILabel=Antaganden_SV€_DataType=STRING€_SourceIndex=18€",
		"VarType=32€ColType=841€AttributeDim=Assumptions€AttributeElemVar=v_Assumptions_0€AttributeAction=Update€AttributeName=??_TC€AttributeType=Alias€_UserVisible=v____TC_19€_UILabel=??_TC€_DataType=STRING€_SourceIndex=19€",
		"VarType=32€ColType=841€AttributeDim=Assumptions€AttributeElemVar=v_Assumptions_0€AttributeAction=Update€AttributeName=Varsay?mlar_TR€AttributeType=Alias€_UserVisible=v_Varsay_mlar_TR_20€_UILabel=Varsay?mlar_TR€_DataType=STRING€_SourceIndex=20€"
	],
	"DataSource":
	{
		"Type":"ASCII",
		"asciiDecimalSeparator":".",
		"asciiDelimiterChar":"\t",
		"asciiDelimiterType":"Character",
		"asciiHeaderRecords":1,
		"asciiQuoteCharacter":"\"",
		"asciiThousandSeparator":",",
		"dataSourceNameForClient":"C:\\Program Files\\IBM\\cognos\\tm1\\samples\\tm1\\GO_New_Stores\\translation files\\assumptions.txt",
		"dataSourceNameForServer":"../translation files/assumptions.txt"
	},
	"Parameters":
	[
		{
			"Name":"param_destroy",
			"Prompt":"Destroy dimensions",
			"Value":0,
			"Type":"Numeric"
		},
		{
			"Name":"param_createIfNotExist",
			"Prompt":"Create dimensions if they do not exist",
			"Value":1,
			"Type":"Numeric"
		}
	],
	"Variables":
	[
		{
			"Name":"v_Assumptions_0",
			"Type":"String",
			"Position":1,
			"StartByte":0,
			"EndByte":0
		},
		{
			"Name":"v_P_edpoklady_CS_1",
			"Type":"String",
			"Position":2,
			"StartByte":0,
			"EndByte":0
		},
		{
			"Name":"v_Foruds_tninger_DA_2",
			"Type":"String",
			"Position":3,
			"StartByte":0,
			"EndByte":0
		},
		{
			"Name":"v__bernahmen_DE_3",
			"Type":"String",
			"Position":4,
			"StartByte":0,
			"EndByte":0
		},
		{
			"Name":"v_Suposiciones_ES_4",
			"Type":"String",
			"Position":5,
			"StartByte":0,
			"EndByte":0
		},
		{
			"Name":"v_Oletukset_FI_5",
			"Type":"String",
			"Position":6,
			"StartByte":0,
			"EndByte":0
		},
		{
			"Name":"v_Hypoth_ses_FR_6",
			"Type":"String",
			"Position":7,
			"StartByte":0,
			"EndByte":0
		},
		{
			"Name":"v____JA_7",
			"Type":"String",
			"Position":8,
			"StartByte":0,
			"EndByte":0
		},
		{
			"Name":"v_Pretpostavke_HR_8",
			"Type":"String",
			"Position":9,
			"StartByte":0,
			"EndByte":0
		},
		{
			"Name":"v_Felt_telez_sek_HU_9",
			"Type":"String",
			"Position":10,
			"StartByte":0,
			"EndByte":0
		},
		{
			"Name":"v_Presupposti_IT_10",
			"Type":"String",
			"Position":11,
			"StartByte":0,
			"EndByte":0
		},
		{
			"Name":"v____KO_11",
			"Type":"String",
			"Position":12,
			"StartByte":0,
			"EndByte":0
		},
		{
			"Name":"v_Forutsetninger_NO_12",
			"Type":"String",
			"Position":13,
			"StartByte":0,
			"EndByte":0
		},
		{
			"Name":"v_Za_o_enia_PL_13",
			"Type":"String",
			"Position":14,
			"StartByte":0,
			"EndByte":0
		},
		{
			"Name":"v_Suposi__es_PT_14",
			"Type":"String",
			"Position":15,
			"StartByte":0,
			"EndByte":0
		},
		{
			"Name":"v_Supozi_ii_RO_15",
			"Type":"String",
			"Position":16,
			"StartByte":0,
			"EndByte":0
		},
		{
			"Name":"v_______________RU_16",
			"Type":"String",
			"Position":17,
			"StartByte":0,
			"EndByte":0
		},
		{
			"Name":"v____SC_17",
			"Type":"String",
			"Position":18,
			"StartByte":0,
			"EndByte":0
		},
		{
			"Name":"v_Antaganden_SV_18",
			"Type":"String",
			"Position":19,
			"StartByte":0,
			"EndByte":0
		},
		{
			"Name":"v____TC_19",
			"Type":"String",
			"Position":20,
			"StartByte":0,
			"EndByte":0
		},
		{
			"Name":"v_Varsay_mlar_TR_20",
			"Type":"String",
			"Position":21,
			"StartByte":0,
			"EndByte":0
		}
	]
}